lpjsmin/__init__.py
lpjsmin/jsmin.py
lpjsmin/tests/__init__.py
lpjsmin/tests/jsfiles/sample1.js
lpjsmin/tests/jsfiles/sample2.js
lpjsmin-0.7.dist-info/METADATA
lpjsmin-0.7.dist-info/WHEEL
lpjsmin-0.7.dist-info/entry_points.txt
lpjsmin-0.7.dist-info/top_level.txt
lpjsmin-0.7.dist-info/RECORD
