Metadata-Version: 2.1
Name: lpjsmin
Version: 0.7
Summary: JS Min script that provides cmd line and python processors
Home-page: https://launchpad.net/lpjsmin
Author: Rick Harding
Author-email: rharding@canonical.com
License: BSD
Keywords: javascript minification compress
Classifier: Programming Language :: Python
Classifier: Programming Language :: Python :: 3
Classifier: Programming Language :: Python :: 3.8
Classifier: Programming Language :: Python :: 3.9
Classifier: Programming Language :: Python :: 3.10
Classifier: Programming Language :: Python :: 3.11
Classifier: Programming Language :: Python :: 3.12
Classifier: Programming Language :: Python :: 3.13
Requires-Dist: argparse
Provides-Extra: test
Requires-Dist: pytest; extra == "test"
